braintrust_proxy/__init__.py
braintrust_proxy/openai/__init__.py
braintrust_proxy/openai/models.py
braintrust_proxy/openai/types.py
braintrust_proxy-0.1.0.dist-info/METADATA
braintrust_proxy-0.1.0.dist-info/WHEEL
braintrust_proxy-0.1.0.dist-info/top_level.txt
braintrust_proxy-0.1.0.dist-info/RECORD
