Metadata-Version: 2.4
Name: braintrust-proxy
Version: 0.1.0
Summary: Provides Python types, Pydantic models, and helpers to extend the OpenAI client for the Braintrust proxy, improving developer experience, typechecking, and editor integration.
Requires-Python: >=3.9
Requires-Dist: openai>=1.79.0
Requires-Dist: pydantic>=2.11.4
